kumiho_cli/__init__.py
kumiho_cli/cli.py
kumiho_cli/py.typed
kumiho_cli-1.0.0.dist-info/METADATA
kumiho_cli-1.0.0.dist-info/WHEEL
kumiho_cli-1.0.0.dist-info/entry_points.txt
kumiho_cli-1.0.0.dist-info/top_level.txt
kumiho_cli-1.0.0.dist-info/RECORD
