Metadata-Version: 2.4
Name: kumiho-cli
Version: 1.0.0
Summary: Command-line tools for Kumiho Cloud asset management
Author-email: Kumiho Clouds <support@kumiho.cloud>
Maintainer-email: Kumiho Clouds <support@kumiho.cloud>
License: Apache-2.0
Project-URL: Homepage, https://kumiho.io
Project-URL: Documentation, https://docs.kumiho.io
Project-URL: Repository, https://github.com/kumihoclouds/kumiho-python
Project-URL: Issues, https://github.com/kumihoclouds/kumiho-python/issues
Project-URL: Changelog, https://github.com/kumihoclouds/kumiho-python/blob/main/kumiho-cli/CHANGELOG.md
Keywords: kumiho,cli,authentication,asset-management,firebase
Classifier: Development Status :: 5 - Production/Stable
Classifier: Intended Audience :: Developers
Classifier: License :: OSI Approved :: Apache Software License
Classifier: Operating System :: OS Independent
Classifier: Programming Language :: Python :: 3
Classifier: Programming Language :: Python :: 3.8
Classifier: Programming Language :: Python :: 3.9
Classifier: Programming Language :: Python :: 3.10
Classifier: Programming Language :: Python :: 3.11
Classifier: Programming Language :: Python :: 3.12
Classifier: Topic :: Software Development :: Libraries :: Python Modules
Classifier: Topic :: System :: Systems Administration :: Authentication/Directory
Classifier: Typing :: Typed
Requires-Python: >=3.8
Requires-Dist: requests>=2.31.0
Provides-Extra: dev
Requires-Dist: pytest>=8.2.0; extra == "dev"
Requires-Dist: pytest-cov>=4.1.0; extra == "dev"
Requires-Dist: mypy>=1.8.0; extra == "dev"
Requires-Dist: types-requests>=2.31.0; extra == "dev"
